.isort.cfg
.travis.yml
CONTRIBUTING.rst
LICENSE.rst
MANIFEST.in
README.rst
appveyor.yml
dev-requirements.txt
setup.py
test_gf256.py
tox.ini
GF256.egg-info/PKG-INFO
GF256.egg-info/SOURCES.txt
GF256.egg-info/dependency_links.txt
GF256.egg-info/top_level.txt
docs/Makefile
docs/conf.py
docs/contributing.rst
docs/index.rst
docs/license.rst
docs/_static/.gitkeep
gf256/__init__.py
gf256/speedups_build.py
scripts/benchmark.py