Metadata-Version: 1.1
Name: GF256
Version: 0.1.0
Summary: An implementation of GF(2**8)
Home-page: https://github.com/DasIch/gf256/
Author: Daniel Neuhäuser
Author-email: ich@danielneuhaeuser.de
License: UNKNOWN
Platform: UNKNOWN
Classifier: License :: OSI Approved :: BSD License
Classifier: Programming Language :: Python :: 3.4
Classifier: Programming Language :: Python :: 3.5
Classifier: Programming Language :: Python :: Implementation :: CPython
